colorez/__init__.py
colorez/colorez.py
colorez-1.1.4.dist-info/METADATA
colorez-1.1.4.dist-info/WHEEL
colorez-1.1.4.dist-info/top_level.txt
colorez-1.1.4.dist-info/RECORD
