Metadata-Version: 2.1
Name: colorez
Version: 1.1.4
Summary: Simple addition of color to the builtin print and input functions
Author: CodingYuno
Project-URL: Source Code, https://github.com/CodingYuno/colorez/
Project-URL: Issue Tracker, https://github.com/CodingYuno/colorez/issues/
Classifier: Development Status :: 5 - Production/Stable
Classifier: Intended Audience :: Developers
Classifier: License :: OSI Approved :: MIT License
Classifier: Operating System :: OS Independent
Classifier: Programming Language :: Python :: 3
Requires-Python: >=3.8
